test/__init__.py
test/test.py
AileenTestFirstAttempt-0.0.2.dist-info/METADATA
AileenTestFirstAttempt-0.0.2.dist-info/WHEEL
AileenTestFirstAttempt-0.0.2.dist-info/top_level.txt
AileenTestFirstAttempt-0.0.2.dist-info/RECORD
