Metadata-Version: 2.1
Name: AileenTestFirstAttempt
Version: 0.0.2
Summary: Streaming video data via networks
Author: Aileen Ouyang
Author-email: <aileenzouyang@gmail.com >
Keywords: python,video,stream,video stream,camera stream,sockets
Classifier: Development Status :: 1 - Planning
Classifier: Intended Audience :: Developers
Classifier: Programming Language :: Python :: 3
Classifier: Operating System :: Unix
Classifier: Operating System :: MacOS :: MacOS X
Classifier: Operating System :: Microsoft :: Windows
Requires-Dist: numpy
Requires-Dist: pandas
